{
  "schema_version": "1.0",
  "books": {
    "b8e3ef689746c15a802aaef29d5e3851a124e797782ad26fe0bea0fcbb492e80": {
      "title": "Rioni di ROMA",
      "slug": "rioni-di-roma",
      "chapters": [
        {
          "label": "Presentazione, di Claudio Rendina",
          "aligned_page_start": 6,
          "aligned_page_end": 6,
          "original_page_start": 6,
          "original_page_end": 6
        },
        {
          "label": "Dalla Roma augustea alla Città leonina",
          "aligned_page_start": 7,
          "aligned_page_end": 6,
          "original_page_start": 7,
          "original_page_end": 6
        },
        {
          "label": "I rioni e i quartieri di Roma, di Mario Sanfilippo",
          "aligned_page_start": 7,
          "aligned_page_end": 11,
          "original_page_start": 7,
          "original_page_end": 11
        },
        {
          "label": "Roma medievale",
          "aligned_page_start": 12,
          "aligned_page_end": 15,
          "original_page_start": 12,
          "original_page_end": 15
        },
        {
          "label": "La città rinascimentale",
          "aligned_page_start": 16,
          "aligned_page_end": 19,
          "original_page_start": 16,
          "original_page_end": 19
        },
        {
          "label": "Roma moderna",
          "aligned_page_start": 20,
          "aligned_page_end": 26,
          "original_page_start": 20,
          "original_page_end": 26
        },
        {
          "label": "Roma capitale",
          "aligned_page_start": 27,
          "aligned_page_end": 35,
          "original_page_start": 27,
          "original_page_end": 35
        },
        {
          "label": "Dalle origini ad oggi",
          "aligned_page_start": 36,
          "aligned_page_end": 39,
          "original_page_start": 36,
          "original_page_end": 39
        },
        {
          "label": "Primo itinerario",
          "aligned_page_start": 40,
          "aligned_page_end": 53,
          "original_page_start": 40,
          "original_page_end": 53
        },
        {
          "label": "Secondo itinerario",
          "aligned_page_start": 54,
          "aligned_page_end": 78,
          "original_page_start": 54,
          "original_page_end": 78
        },
        {
          "label": "Terzo itinerario",
          "aligned_page_start": 79,
          "aligned_page_end": 101,
          "original_page_start": 79,
          "original_page_end": 101
        },
        {
          "label": "Quarto itinerario",
          "aligned_page_start": 102,
          "aligned_page_end": 130,
          "original_page_start": 102,
          "original_page_end": 130
        },
        {
          "label": "Le origini e l'evoluzione urbanistica",
          "aligned_page_start": 131,
          "aligned_page_end": 134,
          "original_page_start": 131,
          "original_page_end": 134
        },
        {
          "label": "Primo itinerario",
          "aligned_page_start": 135,
          "aligned_page_end": 142,
          "original_page_start": 135,
          "original_page_end": 142
        },
        {
          "label": "Secondo itinerario",
          "aligned_page_start": 143,
          "aligned_page_end": 156,
          "original_page_start": 143,
          "original_page_end": 156
        },
        {
          "label": "Terzo itinerario",
          "aligned_page_start": 157,
          "aligned_page_end": 164,
          "original_page_start": 157,
          "original_page_end": 164
        },
        {
          "label": "Quarto itinerario",
          "aligned_page_start": 165,
          "aligned_page_end": 187,
          "original_page_start": 165,
          "original_page_end": 187
        },
        {
          "label": "Quinto itinerario",
          "aligned_page_start": 188,
          "aligned_page_end": 193,
          "original_page_start": 188,
          "original_page_end": 193
        },
        {
          "label": "Sesto itinerario",
          "aligned_page_start": 194,
          "aligned_page_end": 201,
          "original_page_start": 194,
          "original_page_end": 201
        },
        {
          "label": "Dalle origini ad oggi",
          "aligned_page_start": 202,
          "aligned_page_end": 206,
          "original_page_start": 202,
          "original_page_end": 206
        },
        {
          "label": "Primo itinerario",
          "aligned_page_start": 207,
          "aligned_page_end": 228,
          "original_page_start": 207,
          "original_page_end": 228
        },
        {
          "label": "Secondo itinerario",
          "aligned_page_start": 229,
          "aligned_page_end": 242,
          "original_page_start": 229,
          "original_page_end": 242
        },
        {
          "label": "Terzo itinerario",
          "aligned_page_start": 243,
          "aligned_page_end": 263,
          "original_page_start": 243,
          "original_page_end": 263
        },
        {
          "label": "Dalle origini ai tempi moderni",
          "aligned_page_start": 264,
          "aligned_page_end": 269,
          "original_page_start": 264,
          "original_page_end": 269
        },
        {
          "label": "Primo itinerario",
          "aligned_page_start": 270,
          "aligned_page_end": 286,
          "original_page_start": 270,
          "original_page_end": 286
        },
        {
          "label": "Secondo itinerario",
          "aligned_page_start": 287,
          "aligned_page_end": 301,
          "original_page_start": 287,
          "original_page_end": 301
        },
        {
          "label": "Terzo itinerario",
          "aligned_page_start": 302,
          "aligned_page_end": 314,
          "original_page_start": 302,
          "original_page_end": 314
        },
        {
          "label": "Quarto itinerario",
          "aligned_page_start": 315,
          "aligned_page_end": 325,
          "original_page_start": 315,
          "original_page_end": 325
        },
        {
          "label": "Quinto itinerario",
          "aligned_page_start": 326,
          "aligned_page_end": 334,
          "original_page_start": 326,
          "original_page_end": 334
        },
        {
          "label": "Le origini; la storia",
          "aligned_page_start": 335,
          "aligned_page_end": 338,
          "original_page_start": 335,
          "original_page_end": 338
        },
        {
          "label": "Primo itinerario",
          "aligned_page_start": 339,
          "aligned_page_end": 349,
          "original_page_start": 339,
          "original_page_end": 349
        },
        {
          "label": "Secondo itinerario",
          "aligned_page_start": 350,
          "aligned_page_end": 363,
          "original_page_start": 350,
          "original_page_end": 363
        },
        {
          "label": "Terzo itinerario",
          "aligned_page_start": 364,
          "aligned_page_end": 380,
          "original_page_start": 364,
          "original_page_end": 380
        },
        {
          "label": "Ambienti spariti",
          "aligned_page_start": 381,
          "aligned_page_end": 382,
          "original_page_start": 381,
          "original_page_end": 382
        },
        {
          "label": "Le origini, la storia",
          "aligned_page_start": 383,
          "aligned_page_end": 382,
          "original_page_start": 383,
          "original_page_end": 382
        },
        {
          "label": "Rione VI: Parione; di Giorgio Carpaneto",
          "aligned_page_start": 383,
          "aligned_page_end": 392,
          "original_page_start": 383,
          "original_page_end": 392
        },
        {
          "label": "Primo itinerario",
          "aligned_page_start": 393,
          "aligned_page_end": 419,
          "original_page_start": 393,
          "original_page_end": 419
        },
        {
          "label": "Secondo itinerario",
          "aligned_page_start": 420,
          "aligned_page_end": 427,
          "original_page_start": 420,
          "original_page_end": 427
        },
        {
          "label": "Terzo itinerario",
          "aligned_page_start": 428,
          "aligned_page_end": 447,
          "original_page_start": 428,
          "original_page_end": 447
        },
        {
          "label": "Le origini e la storia",
          "aligned_page_start": 448,
          "aligned_page_end": 447,
          "original_page_start": 448,
          "original_page_end": 447
        },
        {
          "label": "Rione VII: Regola; di Mauro Quercioli",
          "aligned_page_start": 448,
          "aligned_page_end": 451,
          "original_page_start": 448,
          "original_page_end": 451
        },
        {
          "label": "Primo itinerario",
          "aligned_page_start": 452,
          "aligned_page_end": 467,
          "original_page_start": 452,
          "original_page_end": 467
        },
        {
          "label": "Secondo itinerario",
          "aligned_page_start": 468,
          "aligned_page_end": 477,
          "original_page_start": 468,
          "original_page_end": 477
        },
        {
          "label": "Terzo itinerario",
          "aligned_page_start": 478,
          "aligned_page_end": 487,
          "original_page_start": 478,
          "original_page_end": 487
        },
        {
          "label": "Quarto itinerario",
          "aligned_page_start": 488,
          "aligned_page_end": 498,
          "original_page_start": 488,
          "original_page_end": 498
        },
        {
          "label": "Dalle origini ad oggi",
          "aligned_page_start": 499,
          "aligned_page_end": 498,
          "original_page_start": 499,
          "original_page_end": 498
        },
        {
          "label": "Rione VIII: S. Eustachio; di Giorgio Carpaneto",
          "aligned_page_start": 499,
          "aligned_page_end": 501,
          "original_page_start": 499,
          "original_page_end": 501
        },
        {
          "label": "Primo itinerario",
          "aligned_page_start": 502,
          "aligned_page_end": 528,
          "original_page_start": 502,
          "original_page_end": 528
        },
        {
          "label": "Secondo itinerario",
          "aligned_page_start": 529,
          "aligned_page_end": 541,
          "original_page_start": 529,
          "original_page_end": 541
        },
        {
          "label": "Terzo itinerario",
          "aligned_page_start": 542,
          "aligned_page_end": 555,
          "original_page_start": 542,
          "original_page_end": 555
        },
        {
          "label": "Dalle origini ai giorni odierni",
          "aligned_page_start": 556,
          "aligned_page_end": 555,
          "original_page_start": 556,
          "original_page_end": 555
        },
        {
          "label": "Rione IX: Pigna, di Carlo Villa",
          "aligned_page_start": 556,
          "aligned_page_end": 559,
          "original_page_start": 556,
          "original_page_end": 559
        },
        {
          "label": "Primo itinerario",
          "aligned_page_start": 560,
          "aligned_page_end": 570,
          "original_page_start": 560,
          "original_page_end": 570
        },
        {
          "label": "Secondo itinerario",
          "aligned_page_start": 571,
          "aligned_page_end": 597,
          "original_page_start": 571,
          "original_page_end": 597
        },
        {
          "label": "Terzo itinerario",
          "aligned_page_start": 598,
          "aligned_page_end": 618,
          "original_page_start": 598,
          "original_page_end": 618
        },
        {
          "label": "Dalle origini ad oggi",
          "aligned_page_start": 619,
          "aligned_page_end": 618,
          "original_page_start": 619,
          "original_page_end": 618
        },
        {
          "label": "Rione X: Campitelli, di Alberto Manodori",
          "aligned_page_start": 619,
          "aligned_page_end": 621,
          "original_page_start": 619,
          "original_page_end": 621
        },
        {
          "label": "Primo itinerario",
          "aligned_page_start": 622,
          "aligned_page_end": 668,
          "original_page_start": 622,
          "original_page_end": 668
        },
        {
          "label": "Secondo itinerario",
          "aligned_page_start": 669,
          "aligned_page_end": 678,
          "original_page_start": 669,
          "original_page_end": 678
        },
        {
          "label": "Terzo itinerario",
          "aligned_page_start": 679,
          "aligned_page_end": 725,
          "original_page_start": 679,
          "original_page_end": 725
        },
        {
          "label": "Dalle origini ad oggi",
          "aligned_page_start": 726,
          "aligned_page_end": 725,
          "original_page_start": 726,
          "original_page_end": 725
        },
        {
          "label": "Rione XI: S. Angelo; di Mauro Quercioli",
          "aligned_page_start": 726,
          "aligned_page_end": 728,
          "original_page_start": 726,
          "original_page_end": 728
        },
        {
          "label": "Primo itinerario",
          "aligned_page_start": 729,
          "aligned_page_end": 745,
          "original_page_start": 729,
          "original_page_end": 745
        },
        {
          "label": "Secondo itinerario",
          "aligned_page_start": 746,
          "aligned_page_end": 759,
          "original_page_start": 746,
          "original_page_end": 759
        },
        {
          "label": "Terzo itinerario",
          "aligned_page_start": 760,
          "aligned_page_end": 766,
          "original_page_start": 760,
          "original_page_end": 766
        },
        {
          "label": "Dalle origini ad oggi",
          "aligned_page_start": 767,
          "aligned_page_end": 766,
          "original_page_start": 767,
          "original_page_end": 766
        },
        {
          "label": "Rione XII: Ripa, di Alberto Manodori",
          "aligned_page_start": 767,
          "aligned_page_end": 767,
          "original_page_start": 767,
          "original_page_end": 767
        },
        {
          "label": "Primo itinerario",
          "aligned_page_start": 768,
          "aligned_page_end": 795,
          "original_page_start": 768,
          "original_page_end": 795
        },
        {
          "label": "Secondo itinerario",
          "aligned_page_start": 796,
          "aligned_page_end": 819,
          "original_page_start": 796,
          "original_page_end": 819
        },
        {
          "label": "Terzo itinerario",
          "aligned_page_start": 820,
          "aligned_page_end": 830,
          "original_page_start": 820,
          "original_page_end": 830
        },
        {
          "label": "Dalle origini ad oggi",
          "aligned_page_start": 831,
          "aligned_page_end": 830,
          "original_page_start": 831,
          "original_page_end": 830
        },
        {
          "label": "Rione XIII: Trastevere; di Giorgio Carpaneto",
          "aligned_page_start": 831,
          "aligned_page_end": 838,
          "original_page_start": 831,
          "original_page_end": 838
        },
        {
          "label": "Primo itinerario",
          "aligned_page_start": 839,
          "aligned_page_end": 853,
          "original_page_start": 839,
          "original_page_end": 853
        },
        {
          "label": "Secondo itinerario",
          "aligned_page_start": 854,
          "aligned_page_end": 875,
          "original_page_start": 854,
          "original_page_end": 875
        },
        {
          "label": "Terzo itinerario",
          "aligned_page_start": 876,
          "aligned_page_end": 887,
          "original_page_start": 876,
          "original_page_end": 887
        },
        {
          "label": "Quarto itinerario",
          "aligned_page_start": 888,
          "aligned_page_end": 901,
          "original_page_start": 888,
          "original_page_end": 901
        },
        {
          "label": "Quinto itinerario",
          "aligned_page_start": 902,
          "aligned_page_end": 909,
          "original_page_start": 902,
          "original_page_end": 909
        },
        {
          "label": "Sesto itinerario",
          "aligned_page_start": 910,
          "aligned_page_end": 923,
          "original_page_start": 910,
          "original_page_end": 923
        },
        {
          "label": "Dalle origini ad oggi",
          "aligned_page_start": 924,
          "aligned_page_end": 923,
          "original_page_start": 924,
          "original_page_end": 923
        },
        {
          "label": "RIONE XIV. BORGO; DI CARLO VILLA",
          "aligned_page_start": 924,
          "aligned_page_end": 929,
          "original_page_start": 924,
          "original_page_end": 929
        },
        {
          "label": "Primo itinerario",
          "aligned_page_start": 930,
          "aligned_page_end": 953,
          "original_page_start": 930,
          "original_page_end": 953
        },
        {
          "label": "Secondo itinerario",
          "aligned_page_start": 954,
          "aligned_page_end": 967,
          "original_page_start": 954,
          "original_page_end": 967
        },
        {
          "label": "Dalle origini ad oggi",
          "aligned_page_start": 968,
          "aligned_page_end": 967,
          "original_page_start": 968,
          "original_page_end": 967
        },
        {
          "label": "RIONE XV. ESQUILINO; DI CLAUDIA CERCHIAI",
          "aligned_page_start": 968,
          "aligned_page_end": 970,
          "original_page_start": 968,
          "original_page_end": 970
        },
        {
          "label": "Primo itinerario",
          "aligned_page_start": 971,
          "aligned_page_end": 981,
          "original_page_start": 971,
          "original_page_end": 981
        },
        {
          "label": "Secondo itinerario",
          "aligned_page_start": 982,
          "aligned_page_end": 999,
          "original_page_start": 982,
          "original_page_end": 999
        },
        {
          "label": "Terzo itinerario",
          "aligned_page_start": 1000,
          "aligned_page_end": 1014,
          "original_page_start": 1000,
          "original_page_end": 1014
        },
        {
          "label": "Dalle origini ad oggi",
          "aligned_page_start": 1015,
          "aligned_page_end": 1014,
          "original_page_start": 1015,
          "original_page_end": 1014
        },
        {
          "label": "RIONE XVI. LUDOVISI, DI GIORGIO CARPANETO",
          "aligned_page_start": 1015,
          "aligned_page_end": 1016,
          "original_page_start": 1015,
          "original_page_end": 1016
        },
        {
          "label": "Primo itinerario",
          "aligned_page_start": 1017,
          "aligned_page_end": 1031,
          "original_page_start": 1017,
          "original_page_end": 1031
        },
        {
          "label": "Secondo itinerario",
          "aligned_page_start": 1032,
          "aligned_page_end": 1037,
          "original_page_start": 1032,
          "original_page_end": 1037
        },
        {
          "label": "Dalle origini ad oggi",
          "aligned_page_start": 1038,
          "aligned_page_end": 1037,
          "original_page_start": 1038,
          "original_page_end": 1037
        },
        {
          "label": "RIONE XVII. SALLUSTIANO; DI CLAUDIA CERCHIAI",
          "aligned_page_start": 1038,
          "aligned_page_end": 1043,
          "original_page_start": 1038,
          "original_page_end": 1043
        },
        {
          "label": "Unico itinerario",
          "aligned_page_start": 1044,
          "aligned_page_end": 1063,
          "original_page_start": 1044,
          "original_page_end": 1063
        },
        {
          "label": "Dalle origini ai nostri giorni",
          "aligned_page_start": 1064,
          "aligned_page_end": 1063,
          "original_page_start": 1064,
          "original_page_end": 1063
        },
        {
          "label": "RIONE XVIII. CASTRO PRETORIO, DI MAURO QUERCIOLI",
          "aligned_page_start": 1064,
          "aligned_page_end": 1065,
          "original_page_start": 1064,
          "original_page_end": 1065
        },
        {
          "label": "Primo itinerario",
          "aligned_page_start": 1066,
          "aligned_page_end": 1085,
          "original_page_start": 1066,
          "original_page_end": 1085
        },
        {
          "label": "Secondo itinerario",
          "aligned_page_start": 1086,
          "aligned_page_end": 1096,
          "original_page_start": 1086,
          "original_page_end": 1096
        },
        {
          "label": "Terzo itinerario",
          "aligned_page_start": 1097,
          "aligned_page_end": 1105,
          "original_page_start": 1097,
          "original_page_end": 1105
        },
        {
          "label": "Dalle origini ad oggi",
          "aligned_page_start": 1106,
          "aligned_page_end": 1105,
          "original_page_start": 1106,
          "original_page_end": 1105
        },
        {
          "label": "RIONE XIX. CELIO; DI CARLO VILLA",
          "aligned_page_start": 1106,
          "aligned_page_end": 1111,
          "original_page_start": 1106,
          "original_page_end": 1111
        },
        {
          "label": "Primo itinerario",
          "aligned_page_start": 1112,
          "aligned_page_end": 1132,
          "original_page_start": 1112,
          "original_page_end": 1132
        },
        {
          "label": "Secondo itinerario",
          "aligned_page_start": 1133,
          "aligned_page_end": 1145,
          "original_page_start": 1133,
          "original_page_end": 1145
        },
        {
          "label": "Dalle origini ad oggi",
          "aligned_page_start": 1146,
          "aligned_page_end": 1145,
          "original_page_start": 1146,
          "original_page_end": 1145
        },
        {
          "label": "RIONE XX. TESTACCIO; DI CLAUDIA CERCHIAI",
          "aligned_page_start": 1146,
          "aligned_page_end": 1150,
          "original_page_start": 1146,
          "original_page_end": 1150
        },
        {
          "label": "Unico itinerario",
          "aligned_page_start": 1151,
          "aligned_page_end": 1172,
          "original_page_start": 1151,
          "original_page_end": 1172
        },
        {
          "label": "Dalle origini ad oggi",
          "aligned_page_start": 1173,
          "aligned_page_end": 1172,
          "original_page_start": 1173,
          "original_page_end": 1172
        },
        {
          "label": "RIONE XXI. S. SABA, DI CLAUDIA CERCHIAI",
          "aligned_page_start": 1173,
          "aligned_page_end": 1174,
          "original_page_start": 1173,
          "original_page_end": 1174
        },
        {
          "label": "Unico itinerario",
          "aligned_page_start": 1175,
          "aligned_page_end": 1197,
          "original_page_start": 1175,
          "original_page_end": 1197
        },
        {
          "label": "Dalle origini ad oggi",
          "aligned_page_start": 1198,
          "aligned_page_end": 1197,
          "original_page_start": 1198,
          "original_page_end": 1197
        },
        {
          "label": "RIONE XXII. PRATI, DI ALBERTO MANODORI",
          "aligned_page_start": 1198,
          "aligned_page_end": 1204,
          "original_page_start": 1198,
          "original_page_end": 1204
        },
        {
          "label": "Unico itinerario",
          "aligned_page_start": 1205,
          "aligned_page_end": 1222,
          "original_page_start": 1205,
          "original_page_end": 1222
        },
        {
          "label": "Indice dei luoghi",
          "aligned_page_start": 1223,
          "aligned_page_end": 1247,
          "original_page_start": 1223,
          "original_page_end": 1247
        }
      ]
    },
    "4a43ad07d57e2833a4c14e4b45051545f46cea8bda42aefe0e7eb1701ea87212": {
      "title": "Storia di ROMA Moderna e Contemporanea",
      "slug": "storia-di-roma-moderna-e-contemp",
      "chapters": [
        {
          "label": "Clemente VII ritorna a Roma",
          "aligned_page_start": 4,
          "aligned_page_end": 3,
          "original_page_start": 7,
          "original_page_end": 6
        },
        {
          "label": "Roma dopo il sacco",
          "aligned_page_start": 4,
          "aligned_page_end": 5,
          "original_page_start": 7,
          "original_page_end": 8
        },
        {
          "label": "Clemente VII incontra Carlo V a Bologna",
          "aligned_page_start": 6,
          "aligned_page_end": 7,
          "original_page_start": 9,
          "original_page_end": 10
        },
        {
          "label": "Le guerre di Clemente VII",
          "aligned_page_start": 8,
          "aligned_page_end": 8,
          "original_page_start": 11,
          "original_page_end": 11
        },
        {
          "label": "Clemente VII si riavvicina alla Francia",
          "aligned_page_start": 9,
          "aligned_page_end": 8,
          "original_page_start": 12,
          "original_page_end": 11
        },
        {
          "label": "Sforza Francesco, duca di Milano,",
          "aligned_page_start": 9,
          "aligned_page_end": 8,
          "original_page_start": 12,
          "original_page_end": 11
        },
        {
          "label": "Solimano II, sultano,",
          "aligned_page_start": 9,
          "aligned_page_end": 11,
          "original_page_start": 12,
          "original_page_end": 14
        },
        {
          "label": "Il Concilio ecumenico",
          "aligned_page_start": 12,
          "aligned_page_end": 11,
          "original_page_start": 15,
          "original_page_end": 14
        },
        {
          "label": "Worms,",
          "aligned_page_start": 12,
          "aligned_page_end": 13,
          "original_page_start": 15,
          "original_page_end": 16
        },
        {
          "label": "Il governo di Clemente VII",
          "aligned_page_start": 14,
          "aligned_page_end": 13,
          "original_page_start": 17,
          "original_page_end": 16
        },
        {
          "label": "Veneto",
          "aligned_page_start": 14,
          "aligned_page_end": 13,
          "original_page_start": 17,
          "original_page_end": 16
        },
        {
          "label": "Zurigo,",
          "aligned_page_start": 14,
          "aligned_page_end": 17,
          "original_page_start": 17,
          "original_page_end": 20
        },
        {
          "label": "La transizione ai tempi nuovi",
          "aligned_page_start": 18,
          "aligned_page_end": 18,
          "original_page_start": 21,
          "original_page_end": 21
        },
        {
          "label": "Alessandro Farnese",
          "aligned_page_start": 19,
          "aligned_page_end": 18,
          "original_page_start": 22,
          "original_page_end": 21
        },
        {
          "label": "Il grande pontificato di Paolo III",
          "aligned_page_start": 19,
          "aligned_page_end": 18,
          "original_page_start": 22,
          "original_page_end": 21
        },
        {
          "label": "L'elezione di Paolo III",
          "aligned_page_start": 19,
          "aligned_page_end": 21,
          "original_page_start": 22,
          "original_page_end": 24
        },
        {
          "label": "L'impegno di Paolo III per l'Italia",
          "aligned_page_start": 22,
          "aligned_page_end": 21,
          "original_page_start": 25,
          "original_page_end": 24
        },
        {
          "label": "Seripando Girolamo, religioso,",
          "aligned_page_start": 22,
          "aligned_page_end": 23,
          "original_page_start": 25,
          "original_page_end": 26
        },
        {
          "label": "La visita di Carlo V a Roma, la guerra in Europa contro i Turchi",
          "aligned_page_start": 24,
          "aligned_page_end": 24,
          "original_page_start": 27,
          "original_page_end": 27
        },
        {
          "label": "Sforza Francesco II, duca di Milano,",
          "aligned_page_start": 25,
          "aligned_page_end": 26,
          "original_page_start": 28,
          "original_page_end": 29
        },
        {
          "label": "La politica religiosa di Paolo III",
          "aligned_page_start": 27,
          "aligned_page_end": 28,
          "original_page_start": 30,
          "original_page_end": 31
        },
        {
          "label": "Il Concilio di Trento",
          "aligned_page_start": 29,
          "aligned_page_end": 28,
          "original_page_start": 32,
          "original_page_end": 31
        },
        {
          "label": "Smalcalda, 16,",
          "aligned_page_start": 29,
          "aligned_page_end": 28,
          "original_page_start": 32,
          "original_page_end": 31
        },
        {
          "label": "Vicenza,",
          "aligned_page_start": 29,
          "aligned_page_end": 31,
          "original_page_start": 32,
          "original_page_end": 34
        },
        {
          "label": "Il nepotismo di Paolo III",
          "aligned_page_start": 32,
          "aligned_page_end": 32,
          "original_page_start": 35,
          "original_page_end": 35
        },
        {
          "label": "Sforza Bosio di Santafiora,",
          "aligned_page_start": 33,
          "aligned_page_end": 35,
          "original_page_start": 36,
          "original_page_end": 38
        },
        {
          "label": "La Roma di Paolo III",
          "aligned_page_start": 36,
          "aligned_page_end": 35,
          "original_page_start": 39,
          "original_page_end": 38
        },
        {
          "label": "Tomarozzi Flaminio",
          "aligned_page_start": 36,
          "aligned_page_end": 37,
          "original_page_start": 39,
          "original_page_end": 40
        },
        {
          "label": "Il governo di Paolo III",
          "aligned_page_start": 38,
          "aligned_page_end": 37,
          "original_page_start": 41,
          "original_page_end": 40
        },
        {
          "label": "Le corti e le feste",
          "aligned_page_start": 38,
          "aligned_page_end": 38,
          "original_page_start": 41,
          "original_page_end": 41
        },
        {
          "label": "Il mecenatismo culturale di Paolo III",
          "aligned_page_start": 39,
          "aligned_page_end": 39,
          "original_page_start": 42,
          "original_page_end": 42
        },
        {
          "label": "Selena Lucio Anneo, scrittore e filosofo,",
          "aligned_page_start": 40,
          "aligned_page_end": 39,
          "original_page_start": 43,
          "original_page_end": 42
        },
        {
          "label": "Trissino Giangiorgio, poeta 20,",
          "aligned_page_start": 40,
          "aligned_page_end": 40,
          "original_page_start": 43,
          "original_page_end": 43
        },
        {
          "label": "Terenzio Afro, commediografo",
          "aligned_page_start": 41,
          "aligned_page_end": 41,
          "original_page_start": 44,
          "original_page_end": 44
        },
        {
          "label": "Il mecenatismo di Paolo III per le arti",
          "aligned_page_start": 42,
          "aligned_page_end": 41,
          "original_page_start": 45,
          "original_page_end": 44
        },
        {
          "label": "Siciolante Girolamo da Sermoneta, pittore,",
          "aligned_page_start": 42,
          "aligned_page_end": 41,
          "original_page_start": 45,
          "original_page_end": 44
        },
        {
          "label": "Tiziano Vecellio, pittore",
          "aligned_page_start": 42,
          "aligned_page_end": 43,
          "original_page_start": 45,
          "original_page_end": 46
        },
        {
          "label": "Vitorchiano,",
          "aligned_page_start": 44,
          "aligned_page_end": 44,
          "original_page_start": 47,
          "original_page_end": 47
        },
        {
          "label": "Roma durante il pontificato di Paolo III",
          "aligned_page_start": 45,
          "aligned_page_end": 44,
          "original_page_start": 48,
          "original_page_end": 47
        },
        {
          "label": "Tomacelli, dinastia",
          "aligned_page_start": 45,
          "aligned_page_end": 45,
          "original_page_start": 48,
          "original_page_end": 48
        },
        {
          "label": "Gli interventi urbanistici",
          "aligned_page_start": 46,
          "aligned_page_end": 48,
          "original_page_start": 49,
          "original_page_end": 51
        },
        {
          "label": "Tristani Giuseppe, architetto",
          "aligned_page_start": 49,
          "aligned_page_end": 51,
          "original_page_start": 52,
          "original_page_end": 54
        },
        {
          "label": "Giulio III",
          "aligned_page_start": 52,
          "aligned_page_end": 51,
          "original_page_start": 55,
          "original_page_end": 54
        },
        {
          "label": "I papati di Giulio III, di Marcello II e di Paolo IV",
          "aligned_page_start": 52,
          "aligned_page_end": 51,
          "original_page_start": 55,
          "original_page_end": 54
        },
        {
          "label": "Il conclave di Giulio III",
          "aligned_page_start": 52,
          "aligned_page_end": 51,
          "original_page_start": 55,
          "original_page_end": 54
        },
        {
          "label": "Siponto,",
          "aligned_page_start": 52,
          "aligned_page_end": 54,
          "original_page_start": 55,
          "original_page_end": 57
        },
        {
          "label": "La riapertura del concilio ecumenico",
          "aligned_page_start": 55,
          "aligned_page_end": 54,
          "original_page_start": 58,
          "original_page_end": 57
        },
        {
          "label": "Zuccari Taddeo, pittore,",
          "aligned_page_start": 55,
          "aligned_page_end": 56,
          "original_page_start": 58,
          "original_page_end": 59
        },
        {
          "label": "Le guerre di Parma e di Siena",
          "aligned_page_start": 57,
          "aligned_page_end": 57,
          "original_page_start": 60,
          "original_page_end": 60
        },
        {
          "label": "Il brevissimo pontificato di Marcello II",
          "aligned_page_start": 58,
          "aligned_page_end": 59,
          "original_page_start": 61,
          "original_page_end": 62
        },
        {
          "label": "Paolo IV",
          "aligned_page_start": 60,
          "aligned_page_end": 60,
          "original_page_start": 63,
          "original_page_end": 63
        },
        {
          "label": "L'inizio del pontificato",
          "aligned_page_start": 61,
          "aligned_page_end": 61,
          "original_page_start": 64,
          "original_page_end": 64
        },
        {
          "label": "La guerra contro la Spagna",
          "aligned_page_start": 62,
          "aligned_page_end": 61,
          "original_page_start": 65,
          "original_page_end": 64
        },
        {
          "label": "Sforza di Santafiora Guido Ascanio, cardinale,",
          "aligned_page_start": 62,
          "aligned_page_end": 61,
          "original_page_start": 65,
          "original_page_end": 64
        },
        {
          "label": "Sforza di Santafiora, dinastia,",
          "aligned_page_start": 62,
          "aligned_page_end": 62,
          "original_page_start": 65,
          "original_page_end": 65
        },
        {
          "label": "Vaucelles",
          "aligned_page_start": 63,
          "aligned_page_end": 63,
          "original_page_start": 66,
          "original_page_end": 66
        },
        {
          "label": "Le riforme",
          "aligned_page_start": 64,
          "aligned_page_end": 63,
          "original_page_start": 67,
          "original_page_end": 66
        },
        {
          "label": "Strozzi Pietro, generale,",
          "aligned_page_start": 64,
          "aligned_page_end": 65,
          "original_page_start": 67,
          "original_page_end": 68
        },
        {
          "label": "La caduta dei Carafa",
          "aligned_page_start": 66,
          "aligned_page_end": 67,
          "original_page_start": 69,
          "original_page_end": 70
        },
        {
          "label": "Il conclave di Pio IV",
          "aligned_page_start": 68,
          "aligned_page_end": 67,
          "original_page_start": 71,
          "original_page_end": 70
        },
        {
          "label": "La restaurazione cattolica: Pio IV e Pio V",
          "aligned_page_start": 68,
          "aligned_page_end": 67,
          "original_page_start": 71,
          "original_page_end": 70
        },
        {
          "label": "Pio IV",
          "aligned_page_start": 68,
          "aligned_page_end": 67,
          "original_page_start": 71,
          "original_page_end": 70
        },
        {
          "label": "Serbelloni Cecilia,",
          "aligned_page_start": 68,
          "aligned_page_end": 67,
          "original_page_start": 71,
          "original_page_end": 70
        },
        {
          "label": "Sforza Massimiliano, duca di Milano,",
          "aligned_page_start": 68,
          "aligned_page_end": 69,
          "original_page_start": 71,
          "original_page_end": 72
        },
        {
          "label": "Serbelloni Giovanni Antonio, cardinale,",
          "aligned_page_start": 70,
          "aligned_page_end": 73,
          "original_page_start": 73,
          "original_page_end": 76
        },
        {
          "label": "Sutri,",
          "aligned_page_start": 74,
          "aligned_page_end": 73,
          "original_page_start": 77,
          "original_page_end": 76
        },
        {
          "label": "Vigevano,",
          "aligned_page_start": 74,
          "aligned_page_end": 73,
          "original_page_start": 77,
          "original_page_end": 76
        },
        {
          "label": "Voghera,",
          "aligned_page_start": 74,
          "aligned_page_end": 79,
          "original_page_start": 77,
          "original_page_end": 82
        },
        {
          "label": "Selim II, sultano,",
          "aligned_page_start": 80,
          "aligned_page_end": 79,
          "original_page_start": 83,
          "original_page_end": 82
        },
        {
          "label": "Solimano il Magnifico, sultano,",
          "aligned_page_start": 80,
          "aligned_page_end": 79,
          "original_page_start": 83,
          "original_page_end": 82
        },
        {
          "label": "Venier Sebastiano, doge",
          "aligned_page_start": 80,
          "aligned_page_end": 82,
          "original_page_start": 83,
          "original_page_end": 85
        },
        {
          "label": "Vieste,",
          "aligned_page_start": 83,
          "aligned_page_end": 83,
          "original_page_start": 86,
          "original_page_end": 86
        },
        {
          "label": "Sforza di Santafiora Costanza,",
          "aligned_page_start": 84,
          "aligned_page_end": 83,
          "original_page_start": 87,
          "original_page_end": 86
        },
        {
          "label": "Sora,",
          "aligned_page_start": 84,
          "aligned_page_end": 83,
          "original_page_start": 87,
          "original_page_end": 86
        },
        {
          "label": "Vignola,",
          "aligned_page_start": 84,
          "aligned_page_end": 86,
          "original_page_start": 87,
          "original_page_end": 89
        },
        {
          "label": "Sisto IV, papa, 45,",
          "aligned_page_start": 87,
          "aligned_page_end": 88,
          "original_page_start": 90,
          "original_page_end": 91
        },
        {
          "label": "Vignola Jacopo Barozzi da, architetto e pittore, 24, 34, 52, 56, 58, 81,",
          "aligned_page_start": 89,
          "aligned_page_end": 89,
          "original_page_start": 92,
          "original_page_end": 92
        },
        {
          "label": "Vasari Giorgio, architetto pittore 43-45, 58,",
          "aligned_page_start": 90,
          "aligned_page_end": 89,
          "original_page_start": 93,
          "original_page_end": 92
        },
        {
          "label": "Zuccari Federico, pittore, 53,",
          "aligned_page_start": 90,
          "aligned_page_end": 90,
          "original_page_start": 93,
          "original_page_end": 93
        },
        {
          "label": "Somaglia Margherita della,",
          "aligned_page_start": 91,
          "aligned_page_end": 93,
          "original_page_start": 94,
          "original_page_end": 96
        },
        {
          "label": "Volterra Francesco Cipriani da, architetto,",
          "aligned_page_start": 94,
          "aligned_page_end": 95,
          "original_page_start": 97,
          "original_page_end": 98
        },
        {
          "label": "Tasso Torquato; poeta 87,",
          "aligned_page_start": 96,
          "aligned_page_end": 99,
          "original_page_start": 99,
          "original_page_end": 102
        },
        {
          "label": "Somma Lombarda,",
          "aligned_page_start": 100,
          "aligned_page_end": 101,
          "original_page_start": 103,
          "original_page_end": 104
        },
        {
          "label": "Spezi Celio, religioso,",
          "aligned_page_start": 102,
          "aligned_page_end": 101,
          "original_page_start": 105,
          "original_page_end": 104
        },
        {
          "label": "Verdun",
          "aligned_page_start": 102,
          "aligned_page_end": 109,
          "original_page_start": 105,
          "original_page_end": 112
        },
        {
          "label": "Sfrondati Paolo Emilio, cardinale, 103,",
          "aligned_page_start": 110,
          "aligned_page_end": 109,
          "original_page_start": 113,
          "original_page_end": 112
        },
        {
          "label": "Vervins",
          "aligned_page_start": 110,
          "aligned_page_end": 113,
          "original_page_start": 113,
          "original_page_end": 116
        },
        {
          "label": "Sulmona,",
          "aligned_page_start": 114,
          "aligned_page_end": 116,
          "original_page_start": 117,
          "original_page_end": 119
        },
        {
          "label": "Tempesta Antonio, architetto",
          "aligned_page_start": 117,
          "aligned_page_end": 118,
          "original_page_start": 120,
          "original_page_end": 121
        },
        {
          "label": "Sigismondo II Vasa, re di Polonia, 100, 113,",
          "aligned_page_start": 119,
          "aligned_page_end": 118,
          "original_page_start": 122,
          "original_page_end": 121
        },
        {
          "label": "Visegrad,",
          "aligned_page_start": 119,
          "aligned_page_end": 120,
          "original_page_start": 122,
          "original_page_end": 123
        },
        {
          "label": "Tilly; generale",
          "aligned_page_start": 121,
          "aligned_page_end": 120,
          "original_page_start": 124,
          "original_page_end": 123
        },
        {
          "label": "Valtellina",
          "aligned_page_start": 121,
          "aligned_page_end": 123,
          "original_page_start": 124,
          "original_page_end": 126
        },
        {
          "label": "Vittorio Amedeo I, duca di Savoia,",
          "aligned_page_start": 124,
          "aligned_page_end": 125,
          "original_page_start": 127,
          "original_page_end": 128
        },
        {
          "label": "Suarez Francesco, teologo,",
          "aligned_page_start": 126,
          "aligned_page_end": 136,
          "original_page_start": 129,
          "original_page_end": 139
        },
        {
          "label": "Strada famiano, letterato,",
          "aligned_page_start": 137,
          "aligned_page_end": 137,
          "original_page_start": 140,
          "original_page_end": 140
        },
        {
          "label": "Westfalia,",
          "aligned_page_start": 138,
          "aligned_page_end": 138,
          "original_page_start": 141,
          "original_page_end": 141
        },
        {
          "label": "Tommaso di Villanova, santo",
          "aligned_page_start": 139,
          "aligned_page_end": 141,
          "original_page_start": 142,
          "original_page_end": 144
        },
        {
          "label": "Vasvâr",
          "aligned_page_start": 142,
          "aligned_page_end": 142,
          "original_page_start": 145,
          "original_page_end": 145
        },
        {
          "label": "Sforza Pallavicino Pietro, biografo, 139,",
          "aligned_page_start": 143,
          "aligned_page_end": 143,
          "original_page_start": 146,
          "original_page_end": 146
        },
        {
          "label": "Tarso",
          "aligned_page_start": 144,
          "aligned_page_end": 149,
          "original_page_start": 147,
          "original_page_end": 152
        },
        {
          "label": "Svezia, 89,",
          "aligned_page_start": 150,
          "aligned_page_end": 153,
          "original_page_start": 153,
          "original_page_end": 156
        },
        {
          "label": "Sobieski Giovanni, generale, 153,",
          "aligned_page_start": 154,
          "aligned_page_end": 154,
          "original_page_start": 157,
          "original_page_end": 157
        },
        {
          "label": "Slavonia,",
          "aligned_page_start": 155,
          "aligned_page_end": 154,
          "original_page_start": 158,
          "original_page_end": 157
        },
        {
          "label": "Transilvania 72,",
          "aligned_page_start": 155,
          "aligned_page_end": 155,
          "original_page_start": 158,
          "original_page_end": 158
        },
        {
          "label": "Terni",
          "aligned_page_start": 156,
          "aligned_page_end": 157,
          "original_page_start": 159,
          "original_page_end": 160
        },
        {
          "label": "Stuart, dinastia,",
          "aligned_page_start": 158,
          "aligned_page_end": 158,
          "original_page_start": 161,
          "original_page_end": 161
        },
        {
          "label": "Spinazzola,",
          "aligned_page_start": 159,
          "aligned_page_end": 159,
          "original_page_start": 162,
          "original_page_end": 162
        },
        {
          "label": "Taranto,",
          "aligned_page_start": 160,
          "aligned_page_end": 160,
          "original_page_start": 163,
          "original_page_end": 163
        },
        {
          "label": "Slankemen,",
          "aligned_page_start": 161,
          "aligned_page_end": 160,
          "original_page_start": 164,
          "original_page_end": 163
        },
        {
          "label": "Zenta,",
          "aligned_page_start": 161,
          "aligned_page_end": 168,
          "original_page_start": 164,
          "original_page_end": 171
        },
        {
          "label": "Utrecht 170,",
          "aligned_page_start": 169,
          "aligned_page_end": 168,
          "original_page_start": 172,
          "original_page_end": 171
        },
        {
          "label": "Zeno Apostolo, poeta,",
          "aligned_page_start": 169,
          "aligned_page_end": 169,
          "original_page_start": 172,
          "original_page_end": 172
        },
        {
          "label": "Sergardi Ludovico, scrittore,",
          "aligned_page_start": 170,
          "aligned_page_end": 170,
          "original_page_start": 173,
          "original_page_end": 173
        },
        {
          "label": "Spinola Giorgio, cardinale,",
          "aligned_page_start": 171,
          "aligned_page_end": 170,
          "original_page_start": 174,
          "original_page_end": 173
        },
        {
          "label": "Svizzera, 17, 100,",
          "aligned_page_start": 171,
          "aligned_page_end": 170,
          "original_page_start": 174,
          "original_page_end": 173
        },
        {
          "label": "Viterbo, 8-9, 17, 34, 162,",
          "aligned_page_start": 171,
          "aligned_page_end": 171,
          "original_page_start": 174,
          "original_page_end": 174
        },
        {
          "label": "Scozia, 82, 126,",
          "aligned_page_start": 172,
          "aligned_page_end": 171,
          "original_page_start": 175,
          "original_page_end": 174
        },
        {
          "label": "Specchi Alessandro, architetto, 173,",
          "aligned_page_start": 172,
          "aligned_page_end": 173,
          "original_page_start": 175,
          "original_page_end": 176
        },
        {
          "label": "Tommaso d'Aquino, santo",
          "aligned_page_start": 174,
          "aligned_page_end": 175,
          "original_page_start": 177,
          "original_page_end": 178
        },
        {
          "label": "Vittorio Amedeo II, duca di Savoia, 164, 170,",
          "aligned_page_start": 176,
          "aligned_page_end": 177,
          "original_page_start": 179,
          "original_page_end": 180
        },
        {
          "label": "Tibet",
          "aligned_page_start": 178,
          "aligned_page_end": 177,
          "original_page_start": 181,
          "original_page_end": 180
        },
        {
          "label": "Turchia",
          "aligned_page_start": 178,
          "aligned_page_end": 178,
          "original_page_start": 181,
          "original_page_end": 181
        },
        {
          "label": "Varsavia 162,",
          "aligned_page_start": 179,
          "aligned_page_end": 181,
          "original_page_start": 182,
          "original_page_end": 184
        },
        {
          "label": "Soria G.B., architetto,",
          "aligned_page_start": 182,
          "aligned_page_end": 184,
          "original_page_start": 185,
          "original_page_end": 187
        },
        {
          "label": "Valenti Gonzaga Silvio, cardinale",
          "aligned_page_start": 185,
          "aligned_page_end": 184,
          "original_page_start": 188,
          "original_page_end": 187
        },
        {
          "label": "Vigri Caterina, santa,",
          "aligned_page_start": 185,
          "aligned_page_end": 186,
          "original_page_start": 188,
          "original_page_end": 189
        },
        {
          "label": "Siria,",
          "aligned_page_start": 187,
          "aligned_page_end": 188,
          "original_page_start": 190,
          "original_page_end": 191
        },
        {
          "label": "Udine",
          "aligned_page_start": 189,
          "aligned_page_end": 188,
          "original_page_start": 192,
          "original_page_end": 191
        },
        {
          "label": "Versailles",
          "aligned_page_start": 189,
          "aligned_page_end": 192,
          "original_page_start": 192,
          "original_page_end": 195
        },
        {
          "label": "Theodoli Girolamo; architetto",
          "aligned_page_start": 193,
          "aligned_page_end": 192,
          "original_page_start": 196,
          "original_page_end": 195
        },
        {
          "label": "Vanvitelli Luigi, architetto",
          "aligned_page_start": 193,
          "aligned_page_end": 192,
          "original_page_start": 196,
          "original_page_end": 195
        },
        {
          "label": "Verschaffelt Pietro, scultore",
          "aligned_page_start": 193,
          "aligned_page_end": 194,
          "original_page_start": 196,
          "original_page_end": 197
        },
        {
          "label": "Sezze,",
          "aligned_page_start": 195,
          "aligned_page_end": 194,
          "original_page_start": 198,
          "original_page_end": 197
        },
        {
          "label": "Spinelli Giuseppe, cardinale,",
          "aligned_page_start": 195,
          "aligned_page_end": 194,
          "original_page_start": 198,
          "original_page_end": 197
        },
        {
          "label": "Torrigiani Luigi, cardinale",
          "aligned_page_start": 195,
          "aligned_page_end": 195,
          "original_page_start": 198,
          "original_page_end": 198
        },
        {
          "label": "Winckelmann Johann Joachim, archeologo,",
          "aligned_page_start": 196,
          "aligned_page_end": 196,
          "original_page_start": 199,
          "original_page_end": 199
        },
        {
          "label": "Stanislao Poniatowski, re di Polonia,",
          "aligned_page_start": 197,
          "aligned_page_end": 196,
          "original_page_start": 200,
          "original_page_end": 199
        },
        {
          "label": "Treviri",
          "aligned_page_start": 197,
          "aligned_page_end": 197,
          "original_page_start": 200,
          "original_page_end": 200
        },
        {
          "label": "Tanucci Bernardo, politico,",
          "aligned_page_start": 198,
          "aligned_page_end": 203,
          "original_page_start": 201,
          "original_page_end": 206
        },
        {
          "label": "Servigliano,",
          "aligned_page_start": 204,
          "aligned_page_end": 204,
          "original_page_start": 207,
          "original_page_end": 207
        },
        {
          "label": "Sertor Gaetano, scrittore,",
          "aligned_page_start": 205,
          "aligned_page_end": 205,
          "original_page_start": 208,
          "original_page_end": 208
        },
        {
          "label": "Subiaco,",
          "aligned_page_start": 206,
          "aligned_page_end": 208,
          "original_page_start": 209,
          "original_page_end": 211
        },
        {
          "label": "Sisto V, papa, 85, 93-97, 99-101, 105, 108, 112, 198, 204, 206,",
          "aligned_page_start": 209,
          "aligned_page_end": 208,
          "original_page_start": 212,
          "original_page_end": 211
        },
        {
          "label": "Unterberger Cristoforo; pittore 206,",
          "aligned_page_start": 209,
          "aligned_page_end": 211,
          "original_page_start": 212,
          "original_page_end": 214
        },
        {
          "label": "Valignani Alessandro, religioso gesuita",
          "aligned_page_start": 212,
          "aligned_page_end": 214,
          "original_page_start": 215,
          "original_page_end": 217
        },
        {
          "label": "Vandea",
          "aligned_page_start": 215,
          "aligned_page_end": 214,
          "original_page_start": 218,
          "original_page_end": 217
        },
        {
          "label": "Zamboni Ludovico,",
          "aligned_page_start": 215,
          "aligned_page_end": 216,
          "original_page_start": 218,
          "original_page_end": 219
        },
        {
          "label": "Zelada Francesco Saverio, cardinale, 205, 215,",
          "aligned_page_start": 217,
          "aligned_page_end": 218,
          "original_page_start": 220,
          "original_page_end": 221
        },
        {
          "label": "Siena, 34, 60-61, 64-65, 82, 140, 220,",
          "aligned_page_start": 219,
          "aligned_page_end": 218,
          "original_page_start": 222,
          "original_page_end": 221
        },
        {
          "label": "Valence",
          "aligned_page_start": 219,
          "aligned_page_end": 220,
          "original_page_start": 222,
          "original_page_end": 223
        },
        {
          "label": "Verona",
          "aligned_page_start": 221,
          "aligned_page_end": 222,
          "original_page_start": 224,
          "original_page_end": 225
        },
        {
          "label": "Urbino 26-27, 129, 162, 168,",
          "aligned_page_start": 223,
          "aligned_page_end": 229,
          "original_page_start": 226,
          "original_page_end": 232
        },
        {
          "label": "Thomas Antoine-Jean-Baptiste, litografo",
          "aligned_page_start": 230,
          "aligned_page_end": 229,
          "original_page_start": 233,
          "original_page_end": 232
        },
        {
          "label": "Valadier Giuseppe, architetto 230-232,",
          "aligned_page_start": 230,
          "aligned_page_end": 233,
          "original_page_start": 233,
          "original_page_end": 236
        },
        {
          "label": "Thorvaldsen Bertel, scultore 233,",
          "aligned_page_start": 234,
          "aligned_page_end": 234,
          "original_page_start": 237,
          "original_page_end": 237
        },
        {
          "label": "Sebastiano Somaglia Giulio cesare della, cardinale,",
          "aligned_page_start": 235,
          "aligned_page_end": 234,
          "original_page_start": 238,
          "original_page_end": 237
        },
        {
          "label": "Severoli Antonio, cardinale,",
          "aligned_page_start": 235,
          "aligned_page_end": 234,
          "original_page_start": 238,
          "original_page_end": 237
        },
        {
          "label": "Somaglia Giulio cesare della, cardinale,",
          "aligned_page_start": 235,
          "aligned_page_end": 235,
          "original_page_start": 238,
          "original_page_end": 238
        },
        {
          "label": "Silvagni David, scrittore, 228, 237,",
          "aligned_page_start": 236,
          "aligned_page_end": 235,
          "original_page_start": 239,
          "original_page_end": 238
        },
        {
          "label": "Vittorio Emanuele I, re di Sardegna, 231,",
          "aligned_page_start": 236,
          "aligned_page_end": 236,
          "original_page_start": 239,
          "original_page_end": 239
        },
        {
          "label": "Supino,",
          "aligned_page_start": 237,
          "aligned_page_end": 240,
          "original_page_start": 240,
          "original_page_end": 243
        },
        {
          "label": "Umbria 58,",
          "aligned_page_start": 241,
          "aligned_page_end": 242,
          "original_page_start": 244,
          "original_page_end": 245
        },
        {
          "label": "Scott Walter, scrittore,",
          "aligned_page_start": 243,
          "aligned_page_end": 242,
          "original_page_start": 246,
          "original_page_end": 245
        },
        {
          "label": "Stendhal, pseudonimo di Beyle, scrittore,",
          "aligned_page_start": 243,
          "aligned_page_end": 242,
          "original_page_start": 246,
          "original_page_end": 245
        },
        {
          "label": "Zanazzo Luigi \"Giggi\", poeta,",
          "aligned_page_start": 243,
          "aligned_page_end": 243,
          "original_page_start": 246,
          "original_page_end": 246
        },
        {
          "label": "Ungarelli Luigi, egittologo",
          "aligned_page_start": 244,
          "aligned_page_end": 243,
          "original_page_start": 247,
          "original_page_end": 246
        },
        {
          "label": "Voltaire pseudonimo di Francois-Marie Arouet, 195, 205,",
          "aligned_page_start": 244,
          "aligned_page_end": 249,
          "original_page_start": 247,
          "original_page_end": 252
        },
        {
          "label": "Spoleto, 126, 159, 226,",
          "aligned_page_start": 250,
          "aligned_page_end": 249,
          "original_page_start": 253,
          "original_page_end": 252
        },
        {
          "label": "Vienna, 12, 162, 214, 223, 231, 244,",
          "aligned_page_start": 250,
          "aligned_page_end": 253,
          "original_page_start": 253,
          "original_page_end": 256
        },
        {
          "label": "Soglia, cardinale,",
          "aligned_page_start": 254,
          "aligned_page_end": 253,
          "original_page_start": 257,
          "original_page_end": 256
        },
        {
          "label": "Spaur, diplomatico,",
          "aligned_page_start": 254,
          "aligned_page_end": 253,
          "original_page_start": 257,
          "original_page_end": 256
        },
        {
          "label": "Sterbini Pietro, politico,",
          "aligned_page_start": 254,
          "aligned_page_end": 255,
          "original_page_start": 257,
          "original_page_end": 258
        },
        {
          "label": "Tréhouart, contrammiraglio",
          "aligned_page_start": 256,
          "aligned_page_end": 256,
          "original_page_start": 259,
          "original_page_end": 259
        },
        {
          "label": "Vecchi C. Augusto, storico",
          "aligned_page_start": 257,
          "aligned_page_end": 256,
          "original_page_start": 260,
          "original_page_end": 259
        },
        {
          "label": "Velletri 39, 183, 191-192, 208,",
          "aligned_page_start": 257,
          "aligned_page_end": 258,
          "original_page_start": 260,
          "original_page_end": 261
        },
        {
          "label": "Tivoli 39, 57, 118, 209,",
          "aligned_page_start": 259,
          "aligned_page_end": 258,
          "original_page_start": 262,
          "original_page_end": 261
        },
        {
          "label": "Valmontone 67,",
          "aligned_page_start": 259,
          "aligned_page_end": 264,
          "original_page_start": 262,
          "original_page_end": 267
        },
        {
          "label": "Tadolini Adamo, scultore,",
          "aligned_page_start": 265,
          "aligned_page_end": 266,
          "original_page_start": 268,
          "original_page_end": 269
        },
        {
          "label": "Toscana 10, 26, 83, 127, 145, 149, 167, 191, 198, 209,",
          "aligned_page_start": 267,
          "aligned_page_end": 271,
          "original_page_start": 270,
          "original_page_end": 274
        },
        {
          "label": "Vespignani, architetto",
          "aligned_page_start": 272,
          "aligned_page_end": 272,
          "original_page_start": 275,
          "original_page_end": 275
        },
        {
          "label": "Tevere, fiume 24, 49, 67, 70, 106, 112, 118, 155, 165, 183, 191, 248, 260,",
          "aligned_page_start": 273,
          "aligned_page_end": 272,
          "original_page_start": 276,
          "original_page_end": 275
        },
        {
          "label": "Tognetti Gaetano, patriota",
          "aligned_page_start": 273,
          "aligned_page_end": 273,
          "original_page_start": 276,
          "original_page_end": 276
        },
        {
          "label": "Sedan,",
          "aligned_page_start": 274,
          "aligned_page_end": 281,
          "original_page_start": 277,
          "original_page_end": 284
        },
        {
          "label": "Vercellana",
          "aligned_page_start": 282,
          "aligned_page_end": 283,
          "original_page_start": 285,
          "original_page_end": 286
        },
        {
          "label": "Venezia 9, 27, 29, 38, 64, 78, 83, 94, 102, 106, 127, 135-136, 142, 157, 159, 170, 176, 197, 214,",
          "aligned_page_start": 284,
          "aligned_page_end": 287,
          "original_page_start": 287,
          "original_page_end": 290
        },
        {
          "label": "Sonzogno Raffaele, giornalista, 289,",
          "aligned_page_start": 288,
          "aligned_page_end": 289,
          "original_page_start": 291,
          "original_page_end": 292
        },
        {
          "label": "Vessella, musicista,",
          "aligned_page_start": 290,
          "aligned_page_end": 295,
          "original_page_start": 293,
          "original_page_end": 298
        },
        {
          "label": "Torlonia Leopoldo, sindaco",
          "aligned_page_start": 296,
          "aligned_page_end": 296,
          "original_page_start": 299,
          "original_page_end": 299
        },
        {
          "label": "Tognetti Angelo; macellaio",
          "aligned_page_start": 297,
          "aligned_page_end": 298,
          "original_page_start": 300,
          "original_page_end": 301
        },
        {
          "label": "Varazze",
          "aligned_page_start": 299,
          "aligned_page_end": 299,
          "original_page_start": 302,
          "original_page_end": 302
        },
        {
          "label": "Tanlongo Bernardo, banchiere,",
          "aligned_page_start": 300,
          "aligned_page_end": 301,
          "original_page_start": 303,
          "original_page_end": 304
        },
        {
          "label": "Serao Matilde, scrittrice,",
          "aligned_page_start": 302,
          "aligned_page_end": 301,
          "original_page_start": 305,
          "original_page_end": 304
        },
        {
          "label": "Sommaruga, editore,",
          "aligned_page_start": 302,
          "aligned_page_end": 303,
          "original_page_start": 305,
          "original_page_end": 306
        },
        {
          "label": "Urbano VIII, papa 125-130, 136, 140-142, 147, 151-154, 159, 283-284, 299, 301,",
          "aligned_page_start": 304,
          "aligned_page_end": 309,
          "original_page_start": 307,
          "original_page_end": 312
        },
        {
          "label": "Umberto I, re d'Italia 285, 293-295, 297, 304, 309,",
          "aligned_page_start": 310,
          "aligned_page_end": 315,
          "original_page_start": 313,
          "original_page_end": 318
        },
        {
          "label": "Wright Wilbur, aviatore,",
          "aligned_page_start": 316,
          "aligned_page_end": 318,
          "original_page_start": 319,
          "original_page_end": 321
        },
        {
          "label": "Tripoli",
          "aligned_page_start": 319,
          "aligned_page_end": 318,
          "original_page_start": 322,
          "original_page_end": 321
        },
        {
          "label": "Tripolitania",
          "aligned_page_start": 319,
          "aligned_page_end": 323,
          "original_page_start": 322,
          "original_page_end": 326
        },
        {
          "label": "Trento 32-33, 45, 52, 56, 58, 62, 74, 86, 94,",
          "aligned_page_start": 324,
          "aligned_page_end": 323,
          "original_page_start": 327,
          "original_page_end": 326
        },
        {
          "label": "Trieste",
          "aligned_page_start": 324,
          "aligned_page_end": 326,
          "original_page_start": 327,
          "original_page_end": 329
        },
        {
          "label": "Sonnino Sidney, politico,",
          "aligned_page_start": 327,
          "aligned_page_end": 326,
          "original_page_start": 330,
          "original_page_end": 329
        },
        {
          "label": "Veio",
          "aligned_page_start": 327,
          "aligned_page_end": 326,
          "original_page_start": 330,
          "original_page_end": 329
        },
        {
          "label": "Wilson Thomas Woodrow, presidente statunitense,",
          "aligned_page_start": 327,
          "aligned_page_end": 328,
          "original_page_start": 330,
          "original_page_end": 331
        },
        {
          "label": "Torino 72, 273,",
          "aligned_page_start": 329,
          "aligned_page_end": 328,
          "original_page_start": 332,
          "original_page_end": 331
        },
        {
          "label": "Turin 72, 273,",
          "aligned_page_start": 329,
          "aligned_page_end": 329,
          "original_page_start": 332,
          "original_page_end": 332
        },
        {
          "label": "Toti Enrico, patriota",
          "aligned_page_start": 330,
          "aligned_page_end": 333,
          "original_page_start": 333,
          "original_page_end": 336
        },
        {
          "label": "Teresa del Bambino Gesù, santa 120,",
          "aligned_page_start": 334,
          "aligned_page_end": 337,
          "original_page_start": 337,
          "original_page_end": 340
        },
        {
          "label": "Trilussa pseudonimo di Carlo Alberto Salustri, poeta",
          "aligned_page_start": 338,
          "aligned_page_end": 341,
          "original_page_start": 341,
          "original_page_end": 344
        },
        {
          "label": "Somalia,",
          "aligned_page_start": 342,
          "aligned_page_end": 343,
          "original_page_start": 345,
          "original_page_end": 346
        },
        {
          "label": "Spagna, 21, 26-27, 32, 61, 65, 67, 75, 80, 82, 83, 100, 138, 144, 149, 153, 156-157, 182-183, 201, 204, 207, 209, 214, 230, 270,",
          "aligned_page_start": 344,
          "aligned_page_end": 343,
          "original_page_start": 347,
          "original_page_end": 346
        },
        {
          "label": "Starace Achille, politico,",
          "aligned_page_start": 344,
          "aligned_page_end": 344,
          "original_page_start": 347,
          "original_page_end": 347
        },
        {
          "label": "Stalin Josiph, politico,",
          "aligned_page_start": 345,
          "aligned_page_end": 347,
          "original_page_start": 348,
          "original_page_end": 350
        },
        {
          "label": "Vittorio Emanuele III, re d'Italia, 309, 313-314, 319, 325, 334-335, 345-347,",
          "aligned_page_start": 348,
          "aligned_page_end": 351,
          "original_page_start": 351,
          "original_page_end": 354
        },
        {
          "label": "Wolff Karl, generale,",
          "aligned_page_start": 352,
          "aligned_page_end": 355,
          "original_page_start": 355,
          "original_page_end": 358
        },
        {
          "label": "Sforza, politico,",
          "aligned_page_start": 356,
          "aligned_page_end": 355,
          "original_page_start": 359,
          "original_page_end": 358
        },
        {
          "label": "Vittorio Emanuele III,",
          "aligned_page_start": 356,
          "aligned_page_end": 358,
          "original_page_start": 359,
          "original_page_end": 361
        },
        {
          "label": "Umberto II di Savoia, re d'Italia",
          "aligned_page_start": 359,
          "aligned_page_end": 358,
          "original_page_start": 362,
          "original_page_end": 361
        },
        {
          "label": "Vittorio Emanuele III,",
          "aligned_page_start": 359,
          "aligned_page_end": 362,
          "original_page_start": 362,
          "original_page_end": 365
        },
        {
          "label": "Squarzina Luigi, regista,",
          "aligned_page_start": 363,
          "aligned_page_end": 362,
          "original_page_start": 366,
          "original_page_end": 365
        },
        {
          "label": "Zareschi Elena, attrice,",
          "aligned_page_start": 363,
          "aligned_page_end": 367,
          "original_page_start": 366,
          "original_page_end": 370
        },
        {
          "label": "Venditti Renato, scrittore",
          "aligned_page_start": 368,
          "aligned_page_end": 371,
          "original_page_start": 371,
          "original_page_end": 374
        },
        {
          "label": "Segni Antonio, politico,",
          "aligned_page_start": 372,
          "aligned_page_end": 377,
          "original_page_start": 375,
          "original_page_end": 380
        },
        {
          "label": "Todi Gianni",
          "aligned_page_start": 378,
          "aligned_page_end": 378,
          "original_page_start": 381,
          "original_page_end": 381
        },
        {
          "label": "Zichitella Martino, nappista,",
          "aligned_page_start": 379,
          "aligned_page_end": 379,
          "original_page_start": 382,
          "original_page_end": 382
        },
        {
          "label": "Tanassi Mario, politico,",
          "aligned_page_start": 380,
          "aligned_page_end": 379,
          "original_page_start": 383,
          "original_page_end": 382
        },
        {
          "label": "Velluto Domenico, poliziotto",
          "aligned_page_start": 380,
          "aligned_page_end": 380,
          "original_page_start": 383,
          "original_page_end": 383
        },
        {
          "label": "Varisco Antonio, colonnello dei carabinieri",
          "aligned_page_start": 381,
          "aligned_page_end": 381,
          "original_page_start": 384,
          "original_page_end": 384
        },
        {
          "label": "Stella,",
          "aligned_page_start": 382,
          "aligned_page_end": 383,
          "original_page_start": 385,
          "original_page_end": 386
        },
        {
          "label": "Viezzer Antonio, colonnello,",
          "aligned_page_start": 384,
          "aligned_page_end": 384,
          "original_page_start": 387,
          "original_page_end": 387
        },
        {
          "label": "Vetere Ugo, sindaco,",
          "aligned_page_start": 385,
          "aligned_page_end": 385,
          "original_page_start": 388,
          "original_page_end": 388
        },
        {
          "label": "Superchi Franco, calciatore,",
          "aligned_page_start": 386,
          "aligned_page_end": 385,
          "original_page_start": 389,
          "original_page_end": 388
        },
        {
          "label": "Tancredi Franco, calciatore,",
          "aligned_page_start": 386,
          "aligned_page_end": 385,
          "original_page_start": 389,
          "original_page_end": 388
        },
        {
          "label": "Valigi Claudio; calciatore",
          "aligned_page_start": 386,
          "aligned_page_end": 385,
          "original_page_start": 389,
          "original_page_end": 388
        },
        {
          "label": "Vierchowod Pietro, calciatore,",
          "aligned_page_start": 386,
          "aligned_page_end": 387,
          "original_page_start": 389,
          "original_page_end": 390
        },
        {
          "label": "Stati Uniti, 348,",
          "aligned_page_start": 388,
          "aligned_page_end": 394,
          "original_page_start": 391,
          "original_page_end": 397
        },
        {
          "label": "Voci Alessandro, prefetto,",
          "aligned_page_start": 395,
          "aligned_page_end": 400,
          "original_page_start": 398,
          "original_page_end": 403
        },
        {
          "label": "Sensini Nestor, calciatore,",
          "aligned_page_start": 401,
          "aligned_page_end": 400,
          "original_page_start": 404,
          "original_page_end": 403
        },
        {
          "label": "Stankovic Dejan, calciatore,",
          "aligned_page_start": 401,
          "aligned_page_end": 402,
          "original_page_start": 404,
          "original_page_end": 405
        },
        {
          "label": "Veltroni Walter, sindaco",
          "aligned_page_start": 403,
          "aligned_page_end": 402,
          "original_page_start": 406,
          "original_page_end": 405
        },
        {
          "label": "Venditti Antonello; cantante",
          "aligned_page_start": 403,
          "aligned_page_end": 403,
          "original_page_start": 406,
          "original_page_end": 406
        },
        {
          "label": "Tommasi Damiano, calciatore",
          "aligned_page_start": 404,
          "aligned_page_end": 403,
          "original_page_start": 407,
          "original_page_end": 406
        },
        {
          "label": "Totti Francesco, calciatore",
          "aligned_page_start": 404,
          "aligned_page_end": 403,
          "original_page_start": 407,
          "original_page_end": 406
        },
        {
          "label": "Zanetti Cristiano, calciatore,",
          "aligned_page_start": 404,
          "aligned_page_end": 403,
          "original_page_start": 407,
          "original_page_end": 406
        },
        {
          "label": "Zebina Jonathan, calciatore,",
          "aligned_page_start": 404,
          "aligned_page_end": 451,
          "original_page_start": 407,
          "original_page_end": 454
        }
      ]
    }
  }
}